nr_openai_observability/__init__.py
nr_openai_observability/build_events.py
nr_openai_observability/error_handling_decorator.py
nr_openai_observability/langchain_callback.py
nr_openai_observability/monitor.py
nr_openai_observability-0.3.1.dist-info/LICENSE
nr_openai_observability-0.3.1.dist-info/METADATA
nr_openai_observability-0.3.1.dist-info/WHEEL
nr_openai_observability-0.3.1.dist-info/RECORD
