Metadata-Version: 2.1
Name: nr-openai-observability
Version: 0.3.1
Summary: A lightweight tool to monitor your OpenAI workload.
Home-page: https://newrelic.com/instant-observability/openai
Keywords: newrelic,observability,openai,gpt,chatGPT,GPT-4,monitor,generative,ai
Author: AIR
Author-email: air-opensource@newrelic.com
Requires-Python: >=3.8.1,<4.0.0
Classifier: Programming Language :: Python :: 3
Classifier: Programming Language :: Python :: 3.9
Classifier: Programming Language :: Python :: 3.10
Classifier: Programming Language :: Python :: 3.11
Requires-Dist: newrelic-telemetry-sdk (>=0.4.0,<0.5.0)
Requires-Dist: openai (>=0.8,<0.30)
Project-URL: Repository, https://github.com/newrelic/nr-openai-observability
